source/__init__.py
source/conf.py
source/_static/__init__.py
tests/__init__.py
tests/test_Refactoring.py
tests/test_equations.py
tests/test_plot.py
tests/test_solver.py
vlax1d/Refactoring.py
vlax1d/__init__.py
vlax1d/equations.py
vlax1d/plot.py
vlax1d/solver.py
vlax1d-0.1.1.dist-info/licenses/LICENSE
vlax1d-0.1.1.dist-info/METADATA
vlax1d-0.1.1.dist-info/WHEEL
vlax1d-0.1.1.dist-info/top_level.txt
vlax1d-0.1.1.dist-info/RECORD
