Metadata-Version: 2.4
Name: vlax1d
Version: 0.1.1
Summary: A fast 1D Vlasov Poisson solver using JAX
Home-page: https://github.com/XYJeff23/1D_Vlasov_JAX_Solver
Author: Jianfeng Ye
Author-email: xyjjeff23@gmail.com
Classifier: Programming Language :: Python :: 3
Classifier: License :: OSI Approved :: MIT License
Classifier: Operating System :: OS Independent
Requires-Python: >=3.7
License-File: LICENSE
Requires-Dist: jax
Requires-Dist: jaxlib
Requires-Dist: diffrax
Requires-Dist: numpy
Requires-Dist: matplotlib
Requires-Dist: scipy
Requires-Dist: pandas
Dynamic: author
Dynamic: author-email
Dynamic: classifier
Dynamic: description
Dynamic: description-content-type
Dynamic: home-page
Dynamic: license-file
Dynamic: requires-dist
Dynamic: requires-python
Dynamic: summary
